bojo/__init__.py
bojo/command_line.py
bojo/config.py
bojo/db.py
bojo/render_utils.py
BoJo-0.1.2.dist-info/METADATA
BoJo-0.1.2.dist-info/WHEEL
BoJo-0.1.2.dist-info/entry_points.txt
BoJo-0.1.2.dist-info/top_level.txt
BoJo-0.1.2.dist-info/RECORD
