Metadata-Version: 2.1
Name: BoJo
Version: 0.1.2
Summary: Command-line tool for bullet journaling
Home-page: https://www.github.com/codekansas/bojo
Author: Benjamin Bolte
Author-email: ben@bolte.cc
License: UNKNOWN
Platform: UNKNOWN
Requires-Dist: click
Requires-Dist: dateparser
Requires-Dist: sqlalchemy
Requires-Dist: termcolor
